{"?1":[{"Scope":"???","Question":"???????????","Answer":"What time is it now?","Hint":"??????????????????????","Explanation":"???????????What time is it now? ??????"},{"Scope":"???","Question":"?????????????","Answer":"What is your name?","Hint":"???????????????????????","Explanation":"????????????What is your name? ??????"},{"Scope":"???","Question":"???????????","Answer":"How old are you?","Hint":"????????????????????","Explanation":"?????????How old are you? ??????"},{"Scope":"???","Question":"???????????","Answer":"Where do you live?","Hint":"?????????????????????","Explanation":"??????????Where do you live? ??????"},{"Scope":"???","Question":"?????????????????","Answer":"What is your favorite food?","Hint":"????????????????????????","Explanation":"?????????????What is your favorite food? ??????"},{"Scope":"???","Question":"?????????????","Answer":"Do you like English?","Hint":"??????????????????????????","Explanation":"???????????????Do you like English? ??????"},{"Scope":"???","Question":"??????????????????","Answer":"What do you want to drink?","Hint":"?????????????????????","Explanation":"??????????What do you want to drink? ??????"},{"Scope":"???","Question":"??????????????","Answer":"Can you play the piano?","Hint":"????????????????????????????","Explanation":"?????????????????Can you play the piano? ??????"},{"Scope":"???","Question":"??????????","Answer":"What day is it today?","Hint":"?????????????????????????","Explanation":"?????????What day is it today? ??????"},{"Scope":"???","Question":"??????????????????","Answer":"Why are you here?","Hint":"?????????????????????????","Explanation":"???????????Why are you here? ????Why??????????"}],"?2":[{"Scope":"There is/are ??","Question":"??????1?????","Answer":"There is a cat in the box.","Hint":"??1????","Explanation":"???1?????????????There is??????"},{"Scope":"There is/are ??","Question":"????????????????","Answer":"There are many books on the desk.","Hint":"???????","Explanation":"????????????????????There are??????"},{"Scope":"There is/are ??","Question":"??????????1??????","Answer":"There is a pen on the table.","Hint":"???1????","Explanation":"????1?????????????There is??????"},{"Scope":"There is/are ??","Question":"??????????????????","Answer":"There are some apples in the basket.","Hint":"?????????","Explanation":"?????????????????????There are??????"},{"Scope":"There is/are ??","Question":"????????1??????","Answer":"There is a big tree in the park.","Hint":"??1????","Explanation":"??????1?????????????There is??????"},{"Scope":"There is/are ??","Question":"????5?????","Answer":"There are five birds in the sky.","Hint":"??5?????","Explanation":"???5?????????????There are??????"},{"Scope":"There is/are ??","Question":"????????1??????","Answer":"There is a beautiful flower in the garden.","Hint":"??1????","Explanation":"???????1?????????????There is??????"},{"Scope":"There is/are ??","Question":"????2?????","Answer":"There are two dogs in the yard.","Hint":"??2????","Explanation":"???2?????????????There are??????"},{"Scope":"There is/are ??","Question":"?????????????1??????","Answer":"There is a problem with my computer.","Hint":"???1????","Explanation":"????1?????????????There is??????"},{"Scope":"There is/are ??","Question":"???????????????","Answer":"There are many stars in the night sky.","Hint":"???????????","Explanation":"????????????????????There are??????"}],"?3":[{"Scope":"?????","Question":"????????????????","Answer":"Do you know where the station is?","Hint":"???????????????????????????","Explanation":"????????????????????????????where????the station????is???Do you know??????????????"},{"Scope":"?????","Question":"??????????????????","Answer":"I don't know what time the train leaves.","Hint":"????????????????????????????","Explanation":"????????????????????????????what time????the train????leaves???I don't know??????????????"},{"Scope":"?????","Question":"??????????????????","Answer":"Could you tell me how I can get to the park?","Hint":"?????????????????????????????","Explanation":"????????????????????????????how????I????can get???Could you tell me??????????????"},{"Scope":"?????","Question":"???????????????????","Answer":"I wonder why he is so sad.","Hint":"?????????????????????????????","Explanation":"????????????????????????????why????he????is???I wonder??????????????"},{"Scope":"?????","Question":"???????????????","Answer":"Please tell me what you want to eat.","Hint":"?????????????????????????","Explanation":"????????????????????????????what????you????want???Please tell me??????????????"},{"Scope":"?????","Question":"????????????????????","Answer":"I asked him who broke the window.","Hint":"??????????????????????????????","Explanation":"????????????????????????????who????he????broke???I asked him??????????????"},{"Scope":"?????","Question":"?????????????????????","Answer":"Do you know how many students are in the class?","Hint":"????????????????????????????????","Explanation":"????????????????????????????how many????students????are???Do you know??????????????"},{"Scope":"?????","Question":"?????????????????","Answer":"I want to know when the movie starts.","Hint":"???????????????????????????","Explanation":"????????????????????????????when????the movie????starts???I want to know??????????????"},{"Scope":"?????","Question":"????????????????????","Answer":"She asked me what my favorite subject was.","Hint":"??????????????????????????????","Explanation":"????????????????????????????what????my favorite subject????was???She asked me??????????????"},{"Scope":"?????","Question":"??????????????????????","Answer":"Could you tell me which way is the post office?","Hint":"?????????????????????????????????","Explanation":"????????????????????????????which way????the post office????is???Could you tell me??????????????"}],"?1":[{"Scope":"?????","Question":"???????????????","Answer":"This is the house that Jack built.","Hint":"?????that????????????","Explanation":"?that?????????????house??????????????????????????????????????????"},{"Scope":"?????","Question":"???????????????????","Answer":"The book which I borrowed from the library is very interesting.","Hint":"?????which????????????","Explanation":"?which?????????????book????????????????????????????????????????????????????"},{"Scope":"?????","Question":"???????????????","Answer":"The girl who is singing is my sister.","Hint":"?????who????????????","Explanation":"?who?????????????girl??????????????????????????????????????????"},{"Scope":"?????","Question":"??????????????????","Answer":"I know a boy whose father is a doctor.","Hint":"?????whose????????????","Explanation":"?whose?????????????boy???????????father??????????????"},{"Scope":"?????","Question":"??????????????","Answer":"The city where I was born is beautiful.","Hint":"????where????????????","Explanation":"?where????????????city???????????I was born???????????????"},{"Scope":"?????","Question":"???????????????","Answer":"This is the reason why I am here.","Hint":"????why????????????","Explanation":"?why????????????reason???????????I am here???????????????"},{"Scope":"?????","Question":"???????????????","Answer":"The day when I met him was sunny.","Hint":"????when????????????","Explanation":"?when????????????day???????????I met him???????????????"},{"Scope":"?????","Question":"?????????????????","Answer":"I have a friend who lives in America.","Hint":"??????????????????","Explanation":"?who????????????friend???????????????????"},{"Scope":"?????","Question":"??????????????","Answer":"The movie that I watched last night was scary.","Hint":"??????????????????","Explanation":"?that????????????movie????????????????????"},{"Scope":"?????","Question":"???????????????????","Answer":"The dog, which was very cute, barked at me.","Hint":"????????????????????????","Explanation":"?which???????????????????dog????????????????"}],"?2":[{"Scope":"??","Question":"??????????????????????","Answer":"This year's harvest is much greater than last year's.","Hint":"??????????????????????????????????","Explanation":"???????????????????????????????much??????????????"},{"Scope":"??","Question":"??????????????","Answer":"My brother is taller than I am.","Hint":"?????????????????","Explanation":"?????????????????????????????than?????I??????I am??????????"},{"Scope":"??","Question":"????????????????","Answer":"This problem is easier than that one.","Hint":"2?????????????????","Explanation":"2???????????????????????"},{"Scope":"??","Question":"????????????????","Answer":"She is less diligent than he is.","Hint":"2????????????????????????????","Explanation":"??????????????????????????????????????less diligent??????"},{"Scope":"??","Question":"??????????????????","Answer":"The population of Tokyo is larger than that of Kyoto.","Hint":"2????????????????","Explanation":"???????????????????????????"},{"Scope":"??","Question":"?????????????????","Answer":"This book is more interesting than that one.","Hint":"2????????????????","Explanation":"2?????????????????????????more interesting??????"},{"Scope":"??","Question":"?????????????????","Answer":"This city is noisier than my hometown.","Hint":"????????????????????","Explanation":"??????????????????????????????????"},{"Scope":"??","Question":"????????????????","Answer":"He is not as tall as his father.","Hint":"?????????????????","Explanation":"???????????????????????????????????as tall as??????"},{"Scope":"??","Question":"????????2???????","Answer":"This car is twice as expensive as that one.","Hint":"2?????????????????????????","Explanation":"2???????????????????2??????????????????twice as expensive as??????"},{"Scope":"??","Question":"???????????????????","Answer":"The red dress is more beautiful than the blue one.","Hint":"?????2??????????????????????????","Explanation":"2???????????????????more beautiful??????"}],"?3":[{"Scope":"???????","Question":"?????????????","Answer":"To learn English is important.","Hint":"???????????????????????","Explanation":"???????????????????????????"},{"Scope":"???????","Question":"?????????????","Answer":"I want to travel abroad.","Hint":"?????????????????????????","Explanation":"????????????????????????????"},{"Scope":"???????","Question":"??????????????","Answer":"He finished reading the book.","Hint":"?????????????????????","Explanation":"????????????????????????????"},{"Scope":"???????","Question":"?????????????????????","Answer":"I am looking forward to seeing you.","Hint":"????????????????????????????","Explanation":"????????????????????????????look forward to ~ing???????"},{"Scope":"???????","Question":"????????????","Answer":"She is good at playing the piano.","Hint":"?????????????????????","Explanation":"????????????????????????????????"},{"Scope":"???????","Question":"???????????????","Answer":"It is difficult to solve this problem.","Hint":"???????????????????????????????","Explanation":"????????????????????????????"},{"Scope":"???????","Question":"????????????????","Answer":"My hobby is collecting stamps.","Hint":"??????????????????????????????????????","Explanation":"????????????????????????????????"},{"Scope":"???????","Question":"?????????","Answer":"Excuse me for being late.","Hint":"??????????????????????????????","Explanation":"??????????????????????????"},{"Scope":"???????","Question":"???????????????","Answer":"I avoid making mistakes.","Hint":"?????????????????????????????","Explanation":"??????????????????????????????"},{"Scope":"???????","Question":"???????????????????","Answer":"She practiced playing the violin every day.","Hint":"??????????????????????????????????","Explanation":"????????????????????????????????????"}]}