{"questions":[{"question":"本州の最北端に位置する都道府県はどこですか。","answer":"choice1","hint":"青森の「あ」は、五十音で一番初め、つまり一番上、北を表す、と覚えるのも一つの方法です。","explanation":"青森県は本州の最北端に位置する都道府県です。津軽海峡を隔てて北海道と向かい合っています。","choice1":"青森県","choice2":"岩手県","choice3":"秋田県","choice4":"山形県","scope":"日本地理の問題です"},{"question":"織田信長が今川義元を破った戦いで、日本の歴史上有名な奇襲作戦が成功した戦いは何ですか。","answer":"choice1","hint":"桶狭間は尾張と三河の国境付近の地名です。","explanation":"織田信長が今川義元を破った戦いは「桶狭間の戦い」です。これは少数の兵で大軍を破った奇襲作戦として非常に有名です。","choice1":"桶狭間の戦い","choice2":"関ヶ原の戦い","choice3":"川中島の戦い","choice4":"長篠の戦い","scope":"日本史の問題です"},{"question":"日本国憲法の三大原則の一つで、国の政治のあり方を最終的に決定する権力が国民にある、という考え方を何と言いますか。","answer":"choice1","hint":"「国」の「民」が「主」権を持つ、という言葉です。","explanation":"日本国憲法の三大原則は「国民主権」「基本的人権の尊重」「平和主義」です。国民主権は、政治の最終決定権が国民にあるという原則です。","choice1":"国民主権","choice2":"民主集中制","choice3":"天皇主権","choice4":"司法の独立","scope":"政治の問題です"}]}