{
  "questions": [
    {
      "question": "2の補数表現において、8ビットの符号付き整数で表現できる値の範囲として正しいものはどれか。",
      "answer": "choice3",
      "hint": "8ビット符号付き整数の2の補数では、最上位ビットが符号ビットになる。最小値は最上位ビットが1で残りが0、最大値は最上位ビットが0で残りが全て1の場合。",
      "explanation": "8ビット2の補数表現では、最上位ビットが符号ビット（0が正、1が負）。最大値は01111111（＝127）、最小値は10000000（＝−128）。よって範囲は−128〜127。正解は[3]。",
      "choice1": "−127 〜 127",
      "choice2": "−128 〜 128",
      "choice3": "−128 〜 127",
      "choice4": "0 〜 255",
      "category": "テクノロジ系",
      "topic": "基礎理論",
      "keyword": "2の補数"
    },
    {
      "question": "ハッシュ表（ハッシュテーブル）におけるオープンアドレス法の説明として正しいものはどれか。",
      "answer": "choice2",
      "hint": "ハッシュ衝突が発生したとき、チェイン法はリストで管理し、オープンアドレス法はテーブル内の別の領域を探索する。それぞれのアプローチの違いを整理しよう。",
      "explanation": "オープンアドレス法は、衝突発生時にハッシュ表の別のインデックスを探索して格納する手法。チェイン法はリンクリストで衝突を解決する。オープンアドレス法は追加メモリ不要だが、負荷率が高いと性能が低下する。正解は[2]。",
      "choice1": "衝突したエントリをリンクリストで管理する手法",
      "choice2": "衝突時にハッシュ表内の別の空きスロットを探して格納する手法",
      "choice3": "ハッシュ関数を複数用意して衝突を回避する手法",
      "choice4": "衝突したエントリを別のハッシュ表にコピーする手法",
      "category": "テクノロジ系",
      "topic": "アルゴリズムとプログラミング",
      "keyword": "ハッシュテーブル"
    },
    {
      "question": "CPUのキャッシュメモリに関する記述として正しいものはどれか。",
      "answer": "choice4",
      "hint": "キャッシュメモリはCPUと主記憶の間に置かれ、頻繁にアクセスされるデータを保持する。ヒット率が高いほど実効アクセス時間は短縮される。",
      "explanation": "キャッシュメモリはCPUと主記憶装置の速度差を緩和するための高速な記憶装置。L1・L2・L3の階層がある。キャッシュヒット率が高いほど主記憶へのアクセス頻度が下がり実効アクセス時間が短縮される。正解は[4]。",
      "choice1": "キャッシュメモリはOSが明示的に管理するため、プログラマが制御できる",
      "choice2": "キャッシュメモリの容量は主記憶装置より大きい",
      "choice3": "キャッシュメモリへの書き込み方式として、ライトスルーはキャッシュのみに書き込む",
      "choice4": "ライトバック方式はキャッシュメモリにのみ書き込み、後で主記憶に反映する",
      "category": "テクノロジ系",
      "topic": "コンピュータ構成要素",
      "keyword": "キャッシュメモリ"
    },
    {
      "question": "RAID5の説明として正しいものはどれか。",
      "answer": "choice1",
      "hint": "RAIDはディスクの冗長化技術。RAID0はストライピングのみ、RAID1はミラーリング、RAID5はストライピングとパリティを組み合わせた手法。",
      "explanation": "RAID5はブロック単位のストライピングとパリティをすべてのディスクに分散して記録する。1台のディスクが故障しても残りのデータとパリティから復元可能。最低3台のディスクが必要。正解は[1]。",
      "choice1": "ストライピングとパリティ情報を全ディスクに分散し、1台の故障からデータを復元できる",
      "choice2": "2台のディスクに同じデータを書き込み、どちらか一方が故障しても継続できる",
      "choice3": "複数のディスクにデータを分散して書き込み、冗長性は持たない",
      "choice4": "2台のディスクが同時に故障してもデータを復元できる",
      "category": "テクノロジ系",
      "topic": "システム構成要素",
      "keyword": "RAID"
    },
    {
      "question": "Linuxのファイルシステムにおけるiノード（inode）の説明として正しいものはどれか。",
      "answer": "choice3",
      "hint": "iノードはUnix系ファイルシステムにおけるファイルのメタデータを管理する構造体。ファイル名とiノードの関係、格納される情報を確認しよう。",
      "explanation": "iノードはファイルのメタデータ（所有者、パーミッション、タイムスタンプ、データブロックへのポインタなど）を格納するデータ構造。ファイル名はディレクトリエントリに格納されiノード番号と対応する。正解は[3]。",
      "choice1": "iノードにはファイル名とファイルの内容が格納される",
      "choice2": "1つのiノードに複数のファイルの内容を格納できる",
      "choice3": "iノードにはファイルのメタデータとデータブロックへのポインタが格納される",
      "choice4": "iノードの数はファイルシステムのフォーマット後に変更できる",
      "category": "テクノロジ系",
      "topic": "ソフトウェア",
      "keyword": "ファイルシステム"
    },
    {
      "question": "関係データベースにおいて、トランザクションの分離レベル「REPEATABLE READ」で防止できない現象として正しいものはどれか。",
      "answer": "choice4",
      "hint": "トランザクションの分離レベルにはREAD UNCOMMITTED、READ COMMITTED、REPEATABLE READ、SERIALIZABLEがある。各レベルで防止できる異常（ダーティリード、ノンリピータブルリード、ファントムリード）を整理しよう。",
      "explanation": "REPEATABLE READはダーティリードとノンリピータブルリードを防止するが、ファントムリード（同じ条件での再読み込みで行数が変わる現象）は防止できない。SERIALIZABLEでのみすべての異常を防げる。正解は[4]。",
      "choice1": "ダーティリード（コミット前のデータを読む現象）",
      "choice2": "ノンリピータブルリード（同じ行の再読みで値が変わる現象）",
      "choice3": "ダーティリードとノンリピータブルリードの両方",
      "choice4": "ファントムリード（再検索で行数が変わる現象）",
      "category": "テクノロジ系",
      "topic": "データベース",
      "keyword": "トランザクション"
    },
    {
      "question": "TCP/IPにおけるARP（Address Resolution Protocol）の役割として正しいものはどれか。",
      "answer": "choice2",
      "hint": "ARPはネットワーク層とデータリンク層の間で動作するプロトコル。IPアドレスとMACアドレスの対応関係を解決する仕組みを理解しよう。",
      "explanation": "ARPはIPアドレスから対応するMACアドレス（物理アドレス）を解決するプロトコル。ブロードキャストでARP要求を送信し、対象ホストがユニキャストでMACアドレスを返す。逆にMACアドレスからIPアドレスを求めるものはRARPという。正解は[2]。",
      "choice1": "ドメイン名をIPアドレスに変換する",
      "choice2": "IPアドレスからMACアドレスを解決する",
      "choice3": "MACアドレスからIPアドレスを解決する",
      "choice4": "IPアドレスからポート番号を解決する",
      "category": "テクノロジ系",
      "topic": "ネットワーク",
      "keyword": "ARP"
    },
    {
      "question": "公開鍵基盤（PKI）においてデジタル証明書に含まれる情報として適切なものはどれか。",
      "answer": "choice1",
      "hint": "デジタル証明書（X.509形式）にはどんな情報が含まれるか。認証局（CA）の役割と証明書の構成要素を整理しよう。",
      "explanation": "デジタル証明書（X.509）にはサブジェクトの公開鍵、発行者（CA）の情報、有効期限、シリアル番号、CAのデジタル署名などが含まれる。秘密鍵は証明書に含まれず、所有者のみが保持する。正解は[1]。",
      "choice1": "サブジェクトの公開鍵と認証局のデジタル署名",
      "choice2": "サブジェクトの秘密鍵と公開鍵のペア",
      "choice3": "通信の暗号化に使われる共通鍵",
      "choice4": "サブジェクトのパスワードハッシュ値",
      "category": "テクノロジ系",
      "topic": "セキュリティ",
      "keyword": "公開鍵基盤"
    },
    {
      "question": "CPUの命令パイプラインにおいてスーパースカラの説明として正しいものはどれか。",
      "answer": "choice3",
      "hint": "パイプラインの高速化技術としてスーパースカラとVLIWがある。スーパースカラは複数の実行ユニットを並列に動作させる方式。",
      "explanation": "スーパースカラは複数の命令実行ユニットを持ち、1クロックサイクルに複数の命令を同時実行できるアーキテクチャ。VLIWはコンパイラが並列実行を制御する方式。スーパースカラはハードウェアが動的に並列実行を判断する。正解は[3]。",
      "choice1": "単一の実行ユニットで命令を順番に実行する従来型アーキテクチャ",
      "choice2": "コンパイラが複数の命令をまとめた超長命令語を生成して並列実行する",
      "choice3": "複数の実行ユニットを持ち、ハードウェアが動的に複数命令を並列実行する",
      "choice4": "命令を複数の段階に分けてパイプライン化する手法",
      "category": "テクノロジ系",
      "topic": "コンピュータ構成要素",
      "keyword": "パイプライン処理"
    },
    {
      "question": "SQLのウィンドウ関数（分析関数）に関する記述として正しいものはどれか。",
      "answer": "choice4",
      "hint": "ウィンドウ関数はGROUP BYと異なり、集計結果を行ごとに保持できる機能。OVER句と組み合わせて使用し、ランキングや累積集計などに使う。",
      "explanation": "ウィンドウ関数はOVER句で定義した「ウィンドウ」に対して集計・順位付けを行い、各行に結果を付加する。GROUP BYと違い元の行数が変わらない。RANK()、ROW_NUMBER()、SUM() OVER()などがある。正解は[4]。",
      "choice1": "GROUP BYと同様に結果行数を集約して減らす",
      "choice2": "WHERE句の後でフィルタリングを行う特殊なサブクエリ",
      "choice3": "テーブルを結合するときに使用する句",
      "choice4": "OVER句で定義した範囲内で集計しながら元の行数を保持する",
      "category": "テクノロジ系",
      "topic": "データベース",
      "keyword": "SQL"
    }
  ]
}
