{"questions":[{"question":"私は先週からずっとこの本を読んでいます。正しい英文を選んでください。","answer":"choice2","hint":"「～以来ずっと」という期間を表す表現では、現在完了形を使います。","explanation":"「since last week（先週からずっと）」は、過去のある時点から現在まで継続している状態を表すため、現在完了形（have + 過去分詞）が適切です。","choice1":"I read this book since last week.","choice2":"I have read this book since last week.","choice3":"I am reading this book since last week.","choice4":"I will read this book since last week.","scope":"時制（現在完了形）の問題です。"},{"question":"私は医者になることを決心しました。この文を英語にするのに最も適切な表現を選んでください。","answer":"choice1","hint":"「～することを決心する」という表現では、動詞の後に不定詞（to + 動詞の原形）が続きます。","explanation":"decideの後には、未来の行為を表す不定詞（to be）が続きます。不定詞の名詞的用法で「～すること」という意味になります。","choice1":"I decided to be a doctor.","choice2":"I decided being a doctor.","choice3":"I decided am a doctor.","choice4":"I decided was a doctor.","scope":"不定詞（名詞的用法）の問題です。"},{"question":"私の趣味は切手を集めることです。この文を英語にするとき、( ) に入るのに最も適切な語句を選んでください。My hobby is ( ) stamps.","answer":"choice2","hint":"be動詞の補語として「～すること」という動名詞を使う場合、動詞のing形を使います。","explanation":"be動詞の補語として「～すること」という内容を述べる場合、動名詞（-ing形）がよく使われます。これは不定詞（to collect）でも可能ですが、動名詞の方が自然な場合が多いです。","choice1":"to collect","choice2":"collecting","choice3":"collect","choice4":"collected","scope":"動名詞の問題です。"},{"question":"この本は多くの人々に読まれています。この文を英語にしたとき、( ) に入るのに最も適切な語句を選んでください。This book ( ) by many people.","answer":"choice2","hint":"「～によって読まれる」という受け身の意味を表す表現を考えましょう。","explanation":"主語「This book」が「読む」という動作をされる側なので、受動態（be動詞 + 過去分詞）を使います。主語が単数で現在形なので「is read」が正解です。","choice1":"reads","choice2":"is read","choice3":"has read","choice4":"read","scope":"受動態の問題です。"},{"question":"彼女は私よりも背が高いです。この文を英語にするとき、( ) に入るのに最も適切な語句を選んでください。She is ( ) than I.","answer":"choice2","hint":"「～よりも…だ」という比較の表現では、比較級を使います。","explanation":"「than I（私よりも）」という表現があるので、比較級を使います。「tall」の比較級は「taller」です。","choice1":"tall","choice2":"taller","choice3":"tallest","choice4":"as tall","scope":"比較（比較級）の問題です。"},{"question":"私は疲れていたので、早く寝ました。この文を英語にするとき、( ) に入るのに最も適切な語句を選んでください。I went to bed early ( ) I was tired.","answer":"choice3","hint":"「～だったので」という理由を表す接続詞を考えましょう。","explanation":"後続の節「I was tired（私は疲れていた）」が、早く寝た理由を示しているので、理由を表す接続詞「because」が適切です。","choice1":"when","choice2":"if","choice3":"because","choice4":"though","scope":"接続詞（because）の問題です。"},{"question":"あれが私が昨日買った本です。この文を英語にするとき、( ) に入るのに最も適切な語句を選んでください。That is the book ( ) I bought yesterday.","answer":"choice3","hint":"先行詞が「もの」である場合に使う関係代名詞を考えましょう。","explanation":"先行詞「the book（本）」は物なので、関係代名詞「which」または「that」を使います。選択肢に「which」があるのでそれが正解です。目的格の関係代名詞は省略することも可能です。","choice1":"who","choice2":"whose","choice3":"which","choice4":"where","scope":"関係代名詞（which）の問題です。"},{"question":"私は彼がどこに住んでいるか知りません。この文を英語にするとき、( ) に入るのに最も適切な語句を選んでください。I don't know ( ) he lives.","answer":"choice3","hint":"間接疑問文では、「疑問詞 + 主語 + 動詞」の語順になります。","explanation":"間接疑問文は「疑問詞 + 主語 + 動詞」の語順になります。「where he lives」が正しい形です。","choice1":"where does","choice2":"where is","choice3":"where","choice4":"where that","scope":"間接疑問文の問題です。"},{"question":"次の英文を日本語に訳してください。My father taught me how to swim.","answer":"choice2","hint":"「teach 人 how to 動詞の原形」の構文の意味を考えましょう。","explanation":"「teach 人 how to 動詞の原形」は「人に～の仕方を教える」という意味になります。したがって、「私の父は泳ぎ方を私に教えてくれました」が最も適切な和訳です。","choice1":"私の父は私が泳ぐ方法を教えてくれました。","choice2":"私の父は泳ぎ方を私に教えてくれました。","choice3":"私の父は泳ぎ方が私に教えられました。","choice4":"私の父は私が泳ぐべきだと言いました。","scope":"英文和訳の問題です。"},{"question":"昨夜、何か面白いことがありましたか？この文を英語にするとき、最も適切な表現を選んでください。","answer":"choice1","hint":"「何か面白いこと」という表現と、過去の出来事を尋ねる疑問文の形を考えましょう。","explanation":"「何か面白いこと」は「anything interesting」と形容詞が後ろから修飾する形になります。過去の出来事に対する疑問文なので「Did anything interesting happen...?」が正しい形です。","choice1":"Did anything interesting happen last night?","choice2":"Did interesting anything happen last night?","choice3":"Was anything interesting happened last night?","choice4":"Anything interesting happened last night?","scope":"和文英訳の問題です。"}]}