{"questions":[{"question":"次の計算をしてください。-5 + (-3) - (-8) + 2 はいくつになりますか。","answer":"choice4","hint":"負の数の引き算は、正の数の足し算と同じです。","explanation":"-5 + (-3) - (-8) + 2 は、-5 - 3 + 8 + 2 と計算できます。-8 + 8 + 2 となるため、答えは 2 です。","choice1":"-14","choice2":"-8","choice3":"0","choice4":"2","scope":"正の数・負の数の問題です"},{"question":"次の式を因数分解してください。x² + 5x + 6","answer":"choice2","hint":"かけて6、足して5になる2つの数を見つけてください。","explanation":"x² + 5x + 6 は、かけて6、足して5になる2つの数 (2と3) を用いて、(x + 2)(x + 3) と因数分解できます。","choice1":"(x + 1)(x + 6)","choice2":"(x + 2)(x + 3)","choice3":"(x - 2)(x - 3)","choice4":"(x - 1)(x + 6)","scope":"展開・因数分解の問題です"},{"question":"√18 + √50 を計算してください。","answer":"choice3","hint":"それぞれの平方根をできるだけ簡単な形にしてください。","explanation":"√18 は √(9 × 2) = 3√2 となります。√50 は √(25 × 2) = 5√2 となります。したがって、3√2 + 5√2 = 8√2 です。","choice1":"√68","choice2":"2√17","choice3":"8√2","choice4":"8√4","scope":"平方根の計算の問題です"},{"question":"ある商品を定価の2割引きで買ったら、1200円でした。この商品の定価はいくらですか。","answer":"choice3","hint":"定価をx円として方程式を立ててください。2割引きは定価の何倍になりますか。","explanation":"定価をx円とすると、2割引きは定価の (1 - 0.2) = 0.8 倍です。したがって、0.8x = 1200 という方程式が立てられます。これを解くと、x = 1200 ÷ 0.8 = 1500 となります。定価は1500円です。","choice1":"960円","choice2":"1440円","choice3":"1500円","choice4":"2400円","scope":"一次方程式の問題です"},{"question":"次の連立方程式を解いてください。{ 2x + y = 7, x - y = 2 }","answer":"choice1","hint":"2つの式を足し合わせると、yが消去できます。","explanation":"2つの式を足すと、(2x + y) + (x - y) = 7 + 2 となり、3x = 9 です。これを解くと x = 3 となります。x = 3 を2つ目の式 (x - y = 2) に代入すると、3 - y = 2 となり、y = 1 です。したがって、x = 3, y = 1 です。","choice1":"x = 3, y = 1","choice2":"x = 2, y = 3","choice3":"x = 4, y = -1","choice4":"x = 1, y = 5","scope":"連立方程式の問題です"},{"question":"二次方程式 x² - 4x + 3 = 0 の解を求めてください。","answer":"choice2","hint":"因数分解を利用するか、解の公式を使ってください。","explanation":"この方程式は (x - 1)(x - 3) = 0 と因数分解できます。したがって、解は x - 1 = 0 または x - 3 = 0 となるので、x = 1 または x = 3 です。","choice1":"x = -1, -3","choice2":"x = 1, 3","choice3":"x = -1, 3","choice4":"x = 1, -3","scope":"二次方程式の問題です"},{"question":"yはxに反比例し、x = 3 のとき y = 6 です。yをxの式で表してください。","answer":"choice3","hint":"反比例の式は y = a/x の形で表されます。aの値を求めてください。","explanation":"反比例の式は y = a/x と表されます。x = 3, y = 6 を代入すると、6 = a/3 となります。これを解くと a = 18 です。したがって、yをxの式で表すと y = 18/x です。","choice1":"y = 2x","choice2":"y = x + 3","choice3":"y = 18/x","choice4":"y = 6x - 3","scope":"比例・反比例の問題です"},{"question":"1から6までの目があるサイコロを2回投げるとき、目の和が7になる確率を求めてください。","answer":"choice2","hint":"全ての目の出方は何通りありますか。また、和が7になる組み合わせを全て書き出してください。","explanation":"サイコロを2回投げるときの目の出方は全部で 6 × 6 = 36 通りです。目の和が7になる組み合わせは、(1,6), (2,5), (3,4), (4,3), (5,2), (6,1) の6通りです。したがって、確率は 6/36 = 1/6 です。","choice1":"1/12","choice2":"1/6","choice3":"1/3","choice4":"1/2","scope":"確率の問題です"},{"question":"あるクラスの生徒5人の数学のテストの点数が、70点、80点、60点、90点、80点でした。この点数の中央値を求めてください。","answer":"choice3","hint":"中央値を求めるためには、まず点数を小さい順に並べ替える必要があります。","explanation":"点数を小さい順に並べると、60点、70点、80点、80点、90点となります。中央値は、真ん中の値なので80点です。","choice1":"70点","choice2":"76点","choice3":"80点","choice4":"90点","scope":"統計の問題です"},{"question":"ある水そうに毎分3リットルの割合で水を入れ続けると、満水になるまでに40分かかります。同じ水そうに毎分xリットルの割合で水を入れ続けると、満水になるまでにy分かかるとします。yをxの式で表してください。","answer":"choice2","hint":"水そうの容量は一定です。容量をxとyの式で表すことを考えてください。","explanation":"水そうの容量は 3リットル/分 × 40分 = 120リットル です。毎分xリットルの割合でy分かかるとすると、容量は x × y とも表せます。したがって、xy = 120 となり、yをxの式で表すと y = 120/x です。","choice1":"y = 3x + 40","choice2":"y = 120/x","choice3":"y = x/120","choice4":"y = 40x/3","scope":"比例・反比例の問題です"}]}